panchang_lib/__init__.py
panchang_lib/panchang.py
panchanga_lib-0.1.0.dist-info/METADATA
panchanga_lib-0.1.0.dist-info/WHEEL
panchanga_lib-0.1.0.dist-info/top_level.txt
panchanga_lib-0.1.0.dist-info/RECORD
